flask_restless/__init__.py
flask_restless/helpers.py
flask_restless/manager.py
flask_restless/search.py
flask_restless/views.py
Flask_Restless_Zx-0.20.0.dist-info/AUTHORS
Flask_Restless_Zx-0.20.0.dist-info/LICENSE.AGPL
Flask_Restless_Zx-0.20.0.dist-info/LICENSE.BSD
Flask_Restless_Zx-0.20.0.dist-info/METADATA
Flask_Restless_Zx-0.20.0.dist-info/WHEEL
Flask_Restless_Zx-0.20.0.dist-info/top_level.txt
Flask_Restless_Zx-0.20.0.dist-info/RECORD
