Metadata-Version: 2.1
Name: Flask-Restless-Zx
Version: 0.20.0
Summary: A Flask extension for easy ReSTful API generation
Home-page: http://github.com/zxlidars/flask-restless-zx
Author: ZX Lidars
Author-email: software@zxlidars.com
License: GNU AGPLv3+ or BSD
Download-URL: http://pypi.python.org/pypi/Flask-Restless-Zx
Keywords: ReST,API,Flask
Platform: any
Classifier: Development Status :: 4 - Beta
Classifier: Environment :: Web Environment
Classifier: Intended Audience :: Developers
Classifier: License :: OSI Approved :: BSD License
Classifier: License :: OSI Approved :: GNU Affero General Public License v3 or later (AGPLv3+)
Classifier: Operating System :: OS Independent
Classifier: Programming Language :: Python
Classifier: Programming Language :: Python :: 2
Classifier: Programming Language :: Python :: 2.6
Classifier: Programming Language :: Python :: 2.7
Classifier: Programming Language :: Python :: 3
Classifier: Programming Language :: Python :: 3.3
Classifier: Programming Language :: Python :: 3.4
Classifier: Topic :: Database :: Front-Ends
Classifier: Topic :: Internet :: WWW/HTTP
Classifier: Topic :: Software Development :: Libraries :: Python Modules
Requires-Dist: flask (>=0.10)
Requires-Dist: sqlalchemy (>=0.8)
Requires-Dist: python-dateutil (>2.0)
Requires-Dist: mimerender (>=0.5.2)
